MANIFEST.in
README.md
examples.py
setup.py
rohrleitung/__init__.py
rohrleitung/rohrleitung.py
rohrleitung.egg-info/PKG-INFO
rohrleitung.egg-info/SOURCES.txt
rohrleitung.egg-info/dependency_links.txt
rohrleitung.egg-info/top_level.txt