Metadata-Version: 1.1
Name: rohrleitung
Version: 0.1.1
Summary: pipelining generators like python, not like shell
Home-page: https://github.com/yggdr/rohrleitung
Author: Konstantin Schukraft
Author-email: konstantin@schukraft.org
License: ISC
Keywords: rohrleitung pipeline pipelines generators iterators
Platform: any
Classifier: Development Status :: 4 - Beta
Classifier: Intended Audience :: Developers
Classifier: License :: OSI Approved :: ISC License (ISCL)
Classifier: Operating System :: OS Independent
Classifier: Programming Language :: Python :: 3 :: Only
Classifier: Programming Language :: Python :: 3.3
Classifier: Programming Language :: Python :: 3.4
Classifier: Programming Language :: Python :: 3.5
Classifier: Programming Language :: Python :: 3.6
Classifier: Topic :: Software Development :: Libraries :: Python Modules
